vnpy_ost/__init__.py
vnpy_ost/api/DntApi.dll
vnpy_ost/api/__init__.py
vnpy_ost/api/libDntApi.so
vnpy_ost/api/libutapi.so
vnpy_ost/api/ost_constant.py
vnpy_ost/api/utapi.dll
vnpy_ost/api/vnostmd.cp310-win_amd64.pyd
vnpy_ost/api/vnostmd.pyd
vnpy_ost/api/vnosttd.cp310-win_amd64.pyd
vnpy_ost/api/vnosttd.pyd
vnpy_ost/api/generator/ost_md_header_define.h
vnpy_ost/api/generator/ost_md_header_function.h
vnpy_ost/api/generator/ost_md_header_on.h
vnpy_ost/api/generator/ost_md_header_process.h
vnpy_ost/api/generator/ost_md_source_function.cpp
vnpy_ost/api/generator/ost_md_source_module.cpp
vnpy_ost/api/generator/ost_md_source_on.cpp
vnpy_ost/api/generator/ost_md_source_process.cpp
vnpy_ost/api/generator/ost_md_source_switch.cpp
vnpy_ost/api/generator/ost_md_source_task.cpp
vnpy_ost/api/generator/ost_td_header_define.h
vnpy_ost/api/generator/ost_td_header_function.h
vnpy_ost/api/generator/ost_td_header_on.h
vnpy_ost/api/generator/ost_td_header_process.h
vnpy_ost/api/generator/ost_td_source_function.cpp
vnpy_ost/api/generator/ost_td_source_module.cpp
vnpy_ost/api/generator/ost_td_source_on.cpp
vnpy_ost/api/generator/ost_td_source_process.cpp
vnpy_ost/api/generator/ost_td_source_switch.cpp
vnpy_ost/api/generator/ost_td_source_task.cpp
vnpy_ost/api/include/ost/DNT_ns.h
vnpy_ost/api/include/ost/SecurityDntL2MDUserApi.h
vnpy_ost/api/include/ost/SecurityDntL2MDUserApiDataStruct.h
vnpy_ost/api/include/ost/SecurityDntL2MDUserApiDataType.h
vnpy_ost/api/include/ost/UTApi.h
vnpy_ost/api/include/ost/UTApiDataType.h
vnpy_ost/api/include/ost/UTApiStruct.h
vnpy_ost/api/include/pybind11/attr.h
vnpy_ost/api/include/pybind11/buffer_info.h
vnpy_ost/api/include/pybind11/cast.h
vnpy_ost/api/include/pybind11/chrono.h
vnpy_ost/api/include/pybind11/common.h
vnpy_ost/api/include/pybind11/complex.h
vnpy_ost/api/include/pybind11/eigen.h
vnpy_ost/api/include/pybind11/embed.h
vnpy_ost/api/include/pybind11/eval.h
vnpy_ost/api/include/pybind11/functional.h
vnpy_ost/api/include/pybind11/iostream.h
vnpy_ost-2.0.1.3.dist-info/LICENSE
vnpy_ost-2.0.1.3.dist-info/METADATA
vnpy_ost-2.0.1.3.dist-info/WHEEL
vnpy_ost-2.0.1.3.dist-info/top_level.txt
vnpy_ost-2.0.1.3.dist-info/RECORD
